./README.md
./pyproject.toml
./tests/__init__.py
./tests/test_tts.py
./tts/__init__.py
./tts/tts.py
getstream_plugins_cartesia-0.1.0.dist-info/METADATA
getstream_plugins_cartesia-0.1.0.dist-info/WHEEL
getstream_plugins_cartesia-0.1.0.dist-info/RECORD
