Metadata-Version: 2.4
Name: getstream-plugins-cartesia
Version: 0.1.0
Summary: Cartesia plugin for GetStream
License-Expression: MIT
Requires-Python: >=3.10
Requires-Dist: cartesia>=2.0.5
Requires-Dist: getstream-plugins-common
Requires-Dist: getstream[webrtc]
